zico/__init__.py
zico-1.0.2.dist-info/LICENSE
zico-1.0.2.dist-info/METADATA
zico-1.0.2.dist-info/WHEEL
zico-1.0.2.dist-info/top_level.txt
zico-1.0.2.dist-info/RECORD
