Metadata-Version: 2.1
Name: zico
Version: 1.0.2
Summary: tes zico
Author: okyx
Author-email: zicolazicola@gmail.com
License: MIT
License-File: LICENSE
